{"assets":{"F6D3558F10DD8D4FE4FD23A98E87B861":{"type":"texture","index":104,"assetRequest":{"type":"slide","state":"outgoing","slide":"DC29992B-367B-4CDF-9BF1-9019806D6517"},"url":{"web":"assets/F6D3558F10DD8D4FE4FD23A98E87B861.svg"},"width":1920,"height":1080},"15801C878EAEE4818C8FC35132644F7C":{"type":"texture","index":105,"assetRequest":{"type":"slide","state":"incoming","slide":"A317B5EF-7F94-4C22-B6E5-4BFEF504CC84"},"url":{"web":"assets/15801C878EAEE4818C8FC35132644F7C.svg"},"width":1920,"height":1080}},"events":[{"effects":[{"beginTime":0,"baseLayer":{"animations":[],"initialState":{"affineTransform":[1,0,0,1,0,0],"masksToBounds":false,"rotation":0,"scale":1,"position":{"pointX":960,"pointY":540},"width":1920,"sublayerTransform":[1,0,0,0,0,1,0,0,0,0,1,0,0,0,0,1],"contentsRect":{"y":0,"x":0,"width":1,"height":1},"opacity":1,"edgeAntialiasingMask":251658240,"height":1080,"hidden":false,"anchorPoint":{"pointX":0.5,"pointY":0.5}},"objectID":"0","layers":[{"animations":[],"initialState":{"affineTransform":[1,0,0,1,0,0],"masksToBounds":false,"rotation":0,"scale":1,"position":{"pointX":960,"pointY":540},"width":1920,"sublayerTransform":[1,0,0,0,0,1,0,0,0,0,1,-0.0003500791246677598,0,0,0,1],"contentsRect":{"y":0,"x":0,"width":1,"height":1},"opacity":1,"edgeAntialiasingMask":251658240,"height":1080,"hidden":false,"anchorPoint":{"pointX":0.5,"pointY":0.5}},"layers":[{"animations":[],"layers":[],"initialState":{"affineTransform":[1,0,0,1,0,0],"masksToBounds":false,"rotation":0,"scale":1,"position":{"pointX":960,"pointY":540},"width":1920,"sublayerTransform":[1,0,0,0,0,1,0,0,0,0,1,0,0,0,0,1],"contentsRect":{"y":0,"x":0,"width":1,"height":1},"opacity":1,"edgeAntialiasingMask":0,"height":1080,"hidden":false,"anchorPoint":{"pointX":0.5,"pointY":0.5}},"texture":"15801C878EAEE4818C8FC35132644F7C"},{"animations":[{"timeOffset":0,"from":{"scalar":false},"beginTime":0,"repeatCount":0,"fillMode":"both","property":"hidden","autoreverses":false,"duration":0.01,"to":{"scalar":true}}],"layers":[],"initialState":{"affineTransform":[1,0,0,1,0,0],"masksToBounds":false,"rotation":0,"scale":1,"position":{"pointX":960,"pointY":540},"width":1920,"sublayerTransform":[1,0,0,0,0,1,0,0,0,0,1,0,0,0,0,1],"contentsRect":{"y":0,"x":0,"width":1,"height":1},"opacity":1,"edgeAntialiasingMask":0,"height":1080,"hidden":false,"anchorPoint":{"pointX":0.5,"pointY":0.5}},"texture":"F6D3558F10DD8D4FE4FD23A98E87B861"}]}]},"effects":[],"duration":0.01,"type":"transition","name":"none","objectID":"0"}],"automaticPlay":false,"hyperlinks":[],"accessibility":[{"text":"IMG_3060.jpg","targetRectangle":{"y":55.18857192993164,"x":376.5050964355469,"width":195.0252532958984,"height":346.1698608398438}},{"text":"VISUAL","targetRectangle":{"y":57.27993297576904,"x":644.7988767623901,"width":88.21875,"height":35.2734375}},{"text":"ACTIVATION","targetRectangle":{"y":93.27993297576904,"x":644.7988767623901,"width":148.1953125,"height":35.2734375}},{"text":"IMG_3092.jpg","targetRectangle":{"y":268.5289001464844,"x":84.39589691162109,"width":195.0252380371094,"height":346.1697998046875}},{"text":"sophiakc.com","targetRectangle":{"y":1027.499987602234,"x":834.0359997749329,"width":251.9279974250794,"height":45}},{"text":"IMG_3035.jpg","targetRectangle":{"y":527.0025024414062,"x":1170.263427734375,"width":193.6331939697266,"height":343.6989135742188}},{"text":"IMG_2974.jpg","targetRectangle":{"y":564.6989135742188,"x":1644.792114257812,"width":195.0252532958984,"height":346.1697998046875}},{"text":"IMG_2975.jpg","targetRectangle":{"y":200.940185546875,"x":1644.792114257812,"width":195.0252532958984,"height":346.1697998046875}},{"text":"IMG_3023.jpg","targetRectangle":{"y":336.5621948242188,"x":923.5318603515625,"width":195.0252532958984,"height":346.1698303222656}},{"text":"IMG_3067.jpg","targetRectangle":{"y":616.1016235351562,"x":745.3922119140625,"width":195.0252532958984,"height":346.1697998046875}},{"text":"IMG_2939.jpg","targetRectangle":{"y":488.6048583984375,"x":1384.672607421875,"width":195.0252532958984,"height":346.1698303222656}},{"text":"OTHER ","targetRectangle":{"y":42.94084072113037,"x":1227.122485160828,"width":87.140625,"height":35.2734375}},{"text":"COMPONENTS","targetRectangle":{"y":78.94084072113037,"x":1227.122485160828,"width":165.421875,"height":35.2734375}},{"text":"ACTIONS WRAPPED ","targetRectangle":{"y":89.53984355926514,"x":1617.23784160614,"width":240,"height":35.2734375}},{"text":"INTO FLOATED CTA","targetRectangle":{"y":125.5398435592651,"x":1617.23784160614,"width":229.453125,"height":35.2734375}},{"text":"IMG_3093.jpg","targetRectangle":{"y":87.26047515869141,"x":138.0953216552734,"width":195.0252380371094,"height":346.1697998046875}},{"text":"IMG_3069.jpg","targetRectangle":{"y":651.494140625,"x":909.0015869140625,"width":195.0252532958984,"height":346.1697998046875}},{"text":"IMG_3073.jpg","targetRectangle":{"y":654.5348510742188,"x":126.6957092285156,"width":195.0252532958984,"height":346.1698303222656}},{"text":"IMG_3081.jpg","targetRectangle":{"y":212.4612731933594,"x":745.3922119140625,"width":195.0252532958984,"height":346.1697998046875}},{"text":"CTA","targetRectangle":{"y":128.5926313400269,"x":59.1483793258667,"width":44.90625,"height":35.2734375}},{"text":"IMG_2977.jpg","targetRectangle":{"y":131.9246673583984,"x":1280.445922851562,"width":195.0252532958984,"height":346.1698303222656}},{"text":"IMG_3098.jpg","targetRectangle":{"y":274.8138732910156,"x":345.5793151855469,"width":195.0252380371094,"height":346.1697998046875}},{"text":"IMG_3102.jpg","targetRectangle":{"y":654.5348510742188,"x":352.9787902832031,"width":195.0252380371094,"height":346.1697998046875}},{"text":"IMG_3036.jpg","targetRectangle":{"y":32.42829513549805,"x":851.6731567382812,"width":193.6331939697266,"height":343.6989135742188}}],"baseLayer":{"animations":[],"initialState":{"affineTransform":[1,0,0,1,0,0],"masksToBounds":false,"rotation":0,"scale":1,"position":{"pointX":960,"pointY":540},"width":1920,"sublayerTransform":[1,0,0,0,0,1,0,0,0,0,1,0,0,0,0,1],"contentsRect":{"y":0,"x":0,"width":1,"height":1},"opacity":1,"edgeAntialiasingMask":251658240,"height":1080,"hidden":false,"anchorPoint":{"pointX":0.5,"pointY":0.5}},"objectID":"0","layers":[{"animations":[],"initialState":{"affineTransform":[1,0,0,1,0,0],"masksToBounds":false,"rotation":0,"scale":1,"position":{"pointX":960,"pointY":540},"width":1920,"sublayerTransform":[1,0,0,0,0,1,0,0,0,0,1,-0.0003500791246677598,0,0,0,1],"contentsRect":{"y":0,"x":0,"width":1,"height":1},"opacity":1,"edgeAntialiasingMask":251658240,"height":1080,"hidden":false,"anchorPoint":{"pointX":0.5,"pointY":0.5}},"layers":[{"animations":[],"layers":[],"initialState":{"affineTransform":[1,0,0,1,0,0],"masksToBounds":false,"rotation":0,"scale":1,"position":{"pointX":960,"pointY":540},"width":1920,"sublayerTransform":[1,0,0,0,0,1,0,0,0,0,1,0,0,0,0,1],"contentsRect":{"y":0,"x":0,"width":1,"height":1},"opacity":1,"edgeAntialiasingMask":0,"height":1080,"hidden":false,"anchorPoint":{"pointX":0.5,"pointY":0.5}},"texture":"F6D3558F10DD8D4FE4FD23A98E87B861"}]}]}}]}